vessel_performance/__init__.py
vessel_performance/analyzer.py
vessel_performance/models.py
vessel_performance/utils.py
vessel_performance-0.1.4.dist-info/LICENSE
vessel_performance-0.1.4.dist-info/METADATA
vessel_performance-0.1.4.dist-info/WHEEL
vessel_performance-0.1.4.dist-info/top_level.txt
vessel_performance-0.1.4.dist-info/RECORD
